dirstats/__about__.py
dirstats/__init__.py
dirstats/dirstats_run.py
dirstats-1.0.1.dist-info/licenses/LICENSE
dirstats-1.0.1.dist-info/METADATA
dirstats-1.0.1.dist-info/WHEEL
dirstats-1.0.1.dist-info/entry_points.txt
dirstats-1.0.1.dist-info/top_level.txt
dirstats-1.0.1.dist-info/RECORD
