Metadata-Version: 2.4
Name: dirstats
Version: 1.0.1
Summary: Analyze a base directory and calculate the total number of files, subfolders, and overall directory size, with optional filtering by one or more file extensions.
Author: Sharrrkkk
Maintainer: Sharrrkkk
License-Expression: MIT
Project-URL: Homepage, https://github.com/Sharrrkkk/DirStats
Project-URL: Documentation, https://github.com/Sharrrkkk/DirStats#README.md
Project-URL: Repository, https://github.com/Sharrrkkk/DirStats
Project-URL: Issues, https://github.com/Sharrrkkk/DirStats/issues
Keywords: cli,filesystem,directory,file-analysis,automation,python-cli,pathlib
Classifier: Development Status :: 5 - Production/Stable
Classifier: Intended Audience :: Developers
Classifier: Intended Audience :: End Users/Desktop
Classifier: Topic :: System :: Filesystems
Classifier: Topic :: Utilities
Classifier: Environment :: Console
Classifier: Programming Language :: Python :: 3
Classifier: Programming Language :: Python :: 3 :: Only
Classifier: Operating System :: OS Independent
Requires-Python: >=3.10
License-File: LICENSE
Dynamic: license-file
